{
  "type": "minecraft:crafting_shapeless",
  "category": "misc",
  "ingredients": [
    {
      "item": "crystechmod:red_tibercrete_powder"
    },
    {
      "item": "crystechmod:red_tibercrete_powder"
    },
    {
      "item": "crystechmod:red_tibercrete_powder"
    },
    {
      "item": "crystechmod:red_tibercrete_powder"
    },
    {
      "item": "crystechmod:red_tibercrete_powder"
    },
    {
      "item": "crystechmod:red_tibercrete_powder"
    },
    {
      "item": "crystechmod:red_tibercrete_powder"
    },
    {
      "item": "crystechmod:red_tibercrete_powder"
    },
    {
      "item": "minecraft:water_bucket"
    }
  ],
  "result": {
    "count": 8,
    "item": "crystechmod:red_tibercrete"
  }
}